thermal_parser/__init__.py
thermal_parser/thermal.py
thermal_parser-20240327.data/data/plugins/exiftool-12.35.exe
thermal_parser-20240327.data/data/plugins/dji_thermal_sdk_v1.4_20220929/License.txt
thermal_parser-20240327.data/data/plugins/dji_thermal_sdk_v1.4_20220929/linux/release_x64/libdirp.so
thermal_parser-20240327.data/data/plugins/dji_thermal_sdk_v1.4_20220929/linux/release_x64/libv_dirp.so
thermal_parser-20240327.data/data/plugins/dji_thermal_sdk_v1.4_20220929/linux/release_x64/libv_girp.so
thermal_parser-20240327.data/data/plugins/dji_thermal_sdk_v1.4_20220929/linux/release_x64/libv_iirp.so
thermal_parser-20240327.data/data/plugins/dji_thermal_sdk_v1.4_20220929/linux/release_x64/libv_list.ini
thermal_parser-20240327.data/data/plugins/dji_thermal_sdk_v1.4_20220929/linux/release_x86/libdirp.so
thermal_parser-20240327.data/data/plugins/dji_thermal_sdk_v1.4_20220929/linux/release_x86/libv_dirp.so
thermal_parser-20240327.data/data/plugins/dji_thermal_sdk_v1.4_20220929/linux/release_x86/libv_girp.so
thermal_parser-20240327.data/data/plugins/dji_thermal_sdk_v1.4_20220929/linux/release_x86/libv_iirp.so
thermal_parser-20240327.data/data/plugins/dji_thermal_sdk_v1.4_20220929/linux/release_x86/libv_list.ini
thermal_parser-20240327.data/data/plugins/dji_thermal_sdk_v1.4_20220929/windows/release_x64/libdirp.dll
thermal_parser-20240327.data/data/plugins/dji_thermal_sdk_v1.4_20220929/windows/release_x64/libdirp.lib
thermal_parser-20240327.data/data/plugins/dji_thermal_sdk_v1.4_20220929/windows/release_x64/libv_dirp.dll
thermal_parser-20240327.data/data/plugins/dji_thermal_sdk_v1.4_20220929/windows/release_x64/libv_dirp.lib
thermal_parser-20240327.data/data/plugins/dji_thermal_sdk_v1.4_20220929/windows/release_x64/libv_girp.dll
thermal_parser-20240327.data/data/plugins/dji_thermal_sdk_v1.4_20220929/windows/release_x64/libv_girp.lib
thermal_parser-20240327.data/data/plugins/dji_thermal_sdk_v1.4_20220929/windows/release_x64/libv_iirp.dll
thermal_parser-20240327.dist-info/LICENSE
thermal_parser-20240327.dist-info/METADATA
thermal_parser-20240327.dist-info/WHEEL
thermal_parser-20240327.dist-info/top_level.txt
thermal_parser-20240327.dist-info/RECORD
